Metadata-Version: 2.1
Name: VehicleRecognition
Version: 0.5.1.1
Summary: Viscan vehicle recognition packages
Home-page: http://192.168.0.73/data_analytics/vehicle-recognition
Author: Onyonka Clifford (vmmr, vehicle colour classification), Rex Mudanya (ANPR, OCR), Jecinta Mulongo (ANPR, OCR)
Author-email: 
Classifier: Development Status :: 5 - Production/Stable
Classifier: Programming Language :: Python :: 3
Classifier: Operating System :: OS Independent
Requires-Python: >=3.0
